{
  "name": "Torre",
  "fields": [
    {
      "fieldName": "numero",
      "fieldType": "Integer"
    }
  ],
  "relationships": [
    {
      "relationshipType": "many-to-one",
      "otherEntityName": "apartamento",
      "otherEntityRelationshipName": "torre",
      "relationshipName": "apartamento"
    }
  ],
  "entityTableName": "torre",
  "dto": "no",
  "pagination": "no",
  "service": "no",
  "jpaMetamodelFiltering": false,
  "fluentMethods": true,
  "readOnly": false,
  "embedded": false,
  "applications": "*",
  "changelogDate": "20210705184521"
}
